mapchete_eo/__init__.py
mapchete_eo/base.py
mapchete_eo/blacklist.txt
mapchete_eo/eostac.py
mapchete_eo/exceptions.py
mapchete_eo/product.py
mapchete_eo/protocols.py
mapchete_eo/settings.py
mapchete_eo/sort.py
mapchete_eo/source.py
mapchete_eo/time.py
mapchete_eo/types.py
mapchete_eo/array/__init__.py
mapchete_eo/array/buffer.py
mapchete_eo/array/color.py
mapchete_eo/array/convert.py
mapchete_eo/cli/__init__.py
mapchete_eo/cli/bounds.py
mapchete_eo/cli/options_arguments.py
mapchete_eo/cli/s2_brdf.py
mapchete_eo/cli/s2_cat_results.py
mapchete_eo/cli/s2_find_broken_products.py
mapchete_eo/cli/s2_jp2_static_catalog.py
mapchete_eo/cli/s2_mask.py
mapchete_eo/cli/s2_mgrs.py
mapchete_eo/cli/s2_rgb.py
mapchete_eo/cli/s2_verify.py
mapchete_eo/cli/static_catalog.py
mapchete_eo/image_operations/__init__.py
mapchete_eo/image_operations/blend_functions.py
mapchete_eo/image_operations/color_correction.py
mapchete_eo/image_operations/compositing.py
mapchete_eo/image_operations/dtype_scale.py
mapchete_eo/image_operations/fillnodata.py
mapchete_eo/image_operations/filters.py
mapchete_eo/image_operations/linear_normalization.py
mapchete_eo/image_operations/sigmoidal.py
mapchete_eo/io/__init__.py
mapchete_eo/io/assets.py
mapchete_eo/io/items.py
mapchete_eo/io/levelled_cubes.py
mapchete_eo/io/path.py
mapchete_eo/io/products.py
mapchete_eo/io/profiles.py
mapchete_eo/platforms/sentinel2/__init__.py
mapchete_eo/platforms/sentinel2/_mapper_registry.py
mapchete_eo/platforms/sentinel2/bandpass_adjustment.py
mapchete_eo/platforms/sentinel2/config.py
mapchete_eo/platforms/sentinel2/driver.py
mapchete_eo/platforms/sentinel2/masks.py
mapchete_eo/platforms/sentinel2/preprocessing_tasks.py
mapchete_eo/platforms/sentinel2/processing_baseline.py
mapchete_eo/platforms/sentinel2/product.py
mapchete_eo/platforms/sentinel2/source.py
mapchete_eo/platforms/sentinel2/types.py
mapchete_eo/platforms/sentinel2/brdf/__init__.py
mapchete_eo/platforms/sentinel2/brdf/config.py
mapchete_eo-2026.1.0.dist-info/METADATA
mapchete_eo-2026.1.0.dist-info/WHEEL
mapchete_eo-2026.1.0.dist-info/entry_points.txt
mapchete_eo-2026.1.0.dist-info/licenses/LICENSE
mapchete_eo-2026.1.0.dist-info/RECORD
