Metadata-Version: 2.4
Name: mapchete-eo
Version: 2026.1.0
Summary: mapchete EO data reader
Project-URL: Homepage, https://gitlab.eox.at/maps/mapchete_eo
Author-email: Joachim Ungar <joachim.ungar@eox.at>, Petr Sevcik <petr.sevcik@eox.at>
License-Expression: MIT
License-File: LICENSE
Classifier: Development Status :: 3 - Alpha
Classifier: Intended Audience :: Developers
Classifier: License :: OSI Approved :: MIT License
Classifier: Programming Language :: Python :: 3.10
Classifier: Programming Language :: Python :: 3.11
Classifier: Programming Language :: Python :: 3.12
Classifier: Programming Language :: Python :: 3.13
Classifier: Topic :: Scientific/Engineering :: GIS
Requires-Dist: click
Requires-Dist: croniter
Requires-Dist: lxml
Requires-Dist: mapchete[complete]>=2025.10.0
Requires-Dist: opencv-python-headless
Requires-Dist: pillow
Requires-Dist: pydantic
Requires-Dist: pygeofilter
Requires-Dist: pystac-client>=0.7.5
Requires-Dist: pystac[urllib3]>=1.12.2
Requires-Dist: retry
Requires-Dist: rtree
Requires-Dist: scipy
Requires-Dist: tqdm
Requires-Dist: xarray
Provides-Extra: docs
Requires-Dist: sphinx; extra == 'docs'
Requires-Dist: sphinx-rtd-theme; extra == 'docs'
Provides-Extra: test
Requires-Dist: pytest; extra == 'test'
Requires-Dist: pytest-coverage; extra == 'test'
Requires-Dist: pytest-lazy-fixtures; extra == 'test'
